[{"Series":"総数","Population":[1760,1598,1483,1296,1188,1078,893,731]},{"Series":"0～4歳","Population":[72,50,44,23,18,31,13,13]},{"Series":"5～9歳","Population":[89,70,49,37,25,17,25,10]},{"Series":"10～14歳","Population":[113,89,70,46,41,20,16,23]},{"Series":"15～19歳","Population":[97,63,59,43,40,34,16,7]},{"Series":"20～24歳","Population":[49,43,35,34,31,28,18,9]},{"Series":"25～29歳","Population":[77,63,44,29,30,25,21,17]},{"Series":"30～34歳","Population":[81,68,53,27,33,33,15,11]},{"Series":"35～39歳","Population":[88,76,70,45,30,26,20,14]},{"Series":"40～44歳","Population":[124,83,73,62,43,31,23,18]},{"Series":"45～49歳","Population":[140,121,80,70,62,43,26,23]},{"Series":"50～54歳","Population":[162,143,116,75,73,56,39,22]},{"Series":"55～59歳","Population":[168,151,135,113,77,73,57,35]},{"Series":"60～64歳","Population":[130,161,145,128,113,72,69,57]},{"Series":"65～69歳","Population":[132,117,157,141,128,109,69,64]},{"Series":"70～74歳","Population":[102,123,114,147,140,121,99,64]},{"Series":"75～79歳","Population":[71,87,111,111,125,134,110,93]},{"Series":"80～84歳","Population":[50,54,64,89,90,114,117,92]},{"Series":"85～89歳以上","Population":[13,30,44,48,55,69,87,87]},{"Series":"90歳以上","Population":[2,6,20,28,34,42,53,72]},{"Series":"年齢不詳","Population":[0,0,0,0,0,0,0,0]}]