[{"Series":"ГЇ▐Ф∙╟","Population":[883,807,731,662,606,547,494]},{"Series":"0ОҐ·4ФґЁ","Population":[19,27,23,19,18,16,15]},{"Series":"5ОҐ·9ФґЁ","Population":[27,19,27,22,19,17,16]},{"Series":"10ОҐ·14ФґЁ","Population":[38,26,18,26,22,19,17]},{"Series":"15ОҐ·19ФґЁ","Population":[29,27,19,13,19,16,13]},{"Series":"20ОҐ·24ФґЁ","Population":[22,23,21,15,10,15,12]},{"Series":"25ОҐ·29ФґЁ","Population":[24,23,23,22,17,13,16]},{"Series":"30ОҐ·34ФґЁ","Population":[32,23,21,22,20,16,12]},{"Series":"35ОҐ·39ФґЁ","Population":[44,36,26,24,24,23,17]},{"Series":"40ОҐ·44ФґЁ","Population":[51,43,35,25,23,23,22]},{"Series":"45ОҐ·49ФґЁ","Population":[38,50,42,35,25,23,23]},{"Series":"50ОҐ·54ФґЁ","Population":[53,40,52,44,37,26,25]},{"Series":"55ОҐ·59ФґЁ","Population":[46,52,39,52,44,36,26]},{"Series":"60ОҐ·64ФґЁ","Population":[57,43,49,37,49,41,34]},{"Series":"65ОҐ·69ФґЁ","Population":[82,58,44,50,38,50,42]},{"Series":"70ОҐ·74ФґЁ","Population":[66,82,59,44,50,38,50]},{"Series":"75ОҐ·79ФґЁ","Population":[74,59,74,53,40,46,35]},{"Series":"80ОҐ·84ФґЁ","Population":[78,63,51,64,47,35,41]},{"Series":"85ОҐ·89ФґЁ","Population":[60,67,56,45,59,43,33]},{"Series":"90ФґЁД╩╔Д╦┼","Population":[43,46,52,50,45,51,45]}]