[{"Series":"ГЇ▐Ф∙╟","Population":[1092,942,810,691,581,486,401]},{"Series":"0ОҐ·4ФґЁ","Population":[22,15,12,10,8,6,5]},{"Series":"5ОҐ·9ФґЁ","Population":[29,21,15,12,9,8,6]},{"Series":"10ОҐ·14ФґЁ","Population":[50,28,21,15,11,9,8]},{"Series":"15ОҐ·19ФґЁ","Population":[30,32,19,14,10,7,6]},{"Series":"20ОҐ·24ФґЁ","Population":[20,18,19,12,9,6,5]},{"Series":"25ОҐ·29ФґЁ","Population":[27,21,20,20,13,9,6]},{"Series":"30ОҐ·34ФґЁ","Population":[31,25,20,19,19,12,9]},{"Series":"35ОҐ·39ФґЁ","Population":[41,28,23,18,16,17,11]},{"Series":"40ОҐ·44ФґЁ","Population":[47,38,26,21,17,15,16]},{"Series":"45ОҐ·49ФґЁ","Population":[64,47,38,26,21,17,15]},{"Series":"50ОҐ·54ФґЁ","Population":[59,60,44,36,24,20,16]},{"Series":"55ОҐ·59ФґЁ","Population":[65,58,60,44,36,24,20]},{"Series":"60ОҐ·64ФґЁ","Population":[99,62,56,57,42,34,23]},{"Series":"65ОҐ·69ФґЁ","Population":[94,95,60,54,55,40,33]},{"Series":"70ОҐ·74ФґЁ","Population":[103,89,90,57,51,52,38]},{"Series":"75ОҐ·79ФґЁ","Population":[97,94,81,83,52,47,49]},{"Series":"80ОҐ·84ФґЁ","Population":[94,85,82,72,74,47,43]},{"Series":"85ОҐ·89ФґЁ","Population":[71,77,71,69,62,64,41]},{"Series":"90ФґЁД╩╔Д╦┼","Population":[49,49,53,52,52,52,51]}]