[{"Series":"þÀÅµò░","Population":[2806,2393,2013,1689,1415,1177,957]},{"Series":"0´¢×4µ¡│","Population":[40,36,29,23,18,14,11]},{"Series":"5´¢×9µ¡│","Population":[43,36,33,26,21,16,13]},{"Series":"10´¢×14µ¡│","Population":[46,45,38,35,28,22,17]},{"Series":"15´¢×19µ¡│","Population":[79,32,32,27,25,20,16]},{"Series":"20´¢×24µ¡│","Population":[51,62,26,25,22,20,16]},{"Series":"25´¢×29µ¡│","Population":[67,40,49,21,20,17,16]},{"Series":"30´¢×34µ¡│","Population":[82,59,35,43,18,18,15]},{"Series":"35´¢×39µ¡│","Population":[84,67,49,30,36,15,15]},{"Series":"40´¢×44µ¡│","Population":[88,81,65,48,29,36,15]},{"Series":"45´¢×49µ¡│","Population":[109,92,85,69,51,31,38]},{"Series":"50´¢×54µ¡│","Population":[154,107,91,84,68,50,30]},{"Series":"55´¢×59µ¡│","Population":[179,152,106,90,83,68,50]},{"Series":"60´¢×64µ¡│","Population":[255,179,152,107,91,84,68]},{"Series":"65´¢×69µ¡│","Population":[255,245,172,147,103,88,81]},{"Series":"70´¢×74µ¡│","Population":[223,238,229,161,138,97,83]},{"Series":"75´¢×79µ¡│","Population":[309,206,221,214,151,130,91]},{"Series":"80´¢×84µ¡│","Population":[342,267,180,195,189,134,116]},{"Series":"85´¢×89µ¡│","Population":[238,258,204,139,154,150,108]},{"Series":"90µ¡│õ╗Ñõ©è","Population":[162,191,217,205,170,167,158]}]