[{"Series":"ГЇ▐Ф∙╟","Population":[555,503,465,440,415,396,375]},{"Series":"0ОҐ·4ФґЁ","Population":[24,26,23,21,20,21,19]},{"Series":"5ОҐ·9ФґЁ","Population":[33,24,26,24,22,21,22]},{"Series":"10ОҐ·14ФґЁ","Population":[44,32,24,26,24,22,21]},{"Series":"15ОҐ·19ФґЁ","Population":[32,13,9,7,7,7,6]},{"Series":"20ОҐ·24ФґЁ","Population":[21,29,17,15,13,13,12]},{"Series":"25ОҐ·29ФґЁ","Population":[13,22,28,19,17,16,16]},{"Series":"30ОҐ·34ФґЁ","Population":[23,13,21,25,18,17,16]},{"Series":"35ОҐ·39ФґЁ","Population":[32,26,15,24,28,21,20]},{"Series":"40ОҐ·44ФґЁ","Population":[25,29,24,14,22,25,19]},{"Series":"45ОҐ·49ФґЁ","Population":[30,26,30,25,15,23,26]},{"Series":"50ОҐ·54ФґЁ","Population":[40,28,25,29,24,15,22]},{"Series":"55ОҐ·59ФґЁ","Population":[36,39,28,25,29,24,14]},{"Series":"60ОҐ·64ФґЁ","Population":[38,37,41,30,26,31,26]},{"Series":"65ОҐ·69ФґЁ","Population":[37,35,34,37,28,24,28]},{"Series":"70ОҐ·74ФґЁ","Population":[29,36,34,33,36,27,24]},{"Series":"75ОҐ·79ФґЁ","Population":[30,25,30,29,28,31,23]},{"Series":"80ОҐ·84ФґЁ","Population":[30,26,21,26,26,25,28]},{"Series":"85ОҐ·89ФґЁ","Population":[20,20,18,15,18,18,18]},{"Series":"90ФґЁД╩╔Д╦┼","Population":[18,17,17,16,14,15,15]}]