[{"Series":"þÀÅµò░","Population":[2449,2228,2014,1812,1616,1418,1233]},{"Series":"0´¢×4µ¡│","Population":[106,88,73,59,48,38,31]},{"Series":"5´¢×9µ¡│","Population":[127,96,79,66,53,43,34]},{"Series":"10´¢×14µ¡│","Population":[124,120,90,75,62,50,41]},{"Series":"15´¢×19µ¡│","Population":[88,91,88,67,56,46,37]},{"Series":"20´¢×24µ¡│","Population":[105,81,84,80,61,51,42]},{"Series":"25´¢×29µ¡│","Population":[113,105,80,83,80,61,50]},{"Series":"30´¢×34µ¡│","Population":[163,103,95,72,75,72,55]},{"Series":"35´¢×39µ¡│","Population":[158,139,88,81,62,64,62]},{"Series":"40´¢×44µ¡│","Population":[173,150,133,84,77,59,61]},{"Series":"45´¢×49µ¡│","Population":[164,171,149,132,84,76,58]},{"Series":"50´¢×54µ¡│","Population":[152,158,165,145,128,81,74]},{"Series":"55´¢×59µ¡│","Population":[177,142,148,155,136,121,76]},{"Series":"60´¢×64µ¡│","Population":[212,165,133,139,145,128,114]},{"Series":"65´¢×69µ¡│","Population":[197,187,146,118,124,130,114]},{"Series":"70´¢×74µ¡│","Population":[109,176,167,132,108,113,119]},{"Series":"75´¢×79µ¡│","Population":[121,89,146,139,110,91,96]},{"Series":"80´¢×84µ¡│","Population":[87,91,68,114,109,87,72]},{"Series":"85´¢×89µ¡│","Population":[51,51,55,42,72,70,57]},{"Series":"90µ¡│õ╗Ñõ©è","Population":[22,25,27,29,26,37,40]}]