[{"Series":"þÀÅµò░","Population":[2024,1762,1534,1332,1143,974,824]},{"Series":"0´¢×4µ¡│","Population":[67,53,40,32,24,18,13]},{"Series":"5´¢×9µ¡│","Population":[75,67,53,40,32,25,18]},{"Series":"10´¢×14µ¡│","Population":[92,68,61,48,37,29,22]},{"Series":"15´¢×19µ¡│","Population":[53,55,40,36,28,22,17]},{"Series":"20´¢×24µ¡│","Population":[49,36,38,28,25,20,15]},{"Series":"25´¢×29µ¡│","Population":[69,56,42,43,32,29,23]},{"Series":"30´¢×34µ¡│","Population":[100,70,57,42,44,32,29]},{"Series":"35´¢×39µ¡│","Population":[83,86,61,50,37,38,28]},{"Series":"40´¢×44µ¡│","Population":[141,80,83,59,48,35,37]},{"Series":"45´¢×49µ¡│","Population":[114,134,76,80,57,46,34]},{"Series":"50´¢×54µ¡│","Population":[142,109,129,74,77,55,44]},{"Series":"55´¢×59µ¡│","Population":[126,139,107,127,73,76,54]},{"Series":"60´¢×64µ¡│","Population":[163,121,134,104,123,71,74]},{"Series":"65´¢×69µ¡│","Population":[203,150,112,125,97,115,66]},{"Series":"70´¢×74µ¡│","Population":[166,192,143,107,120,94,111]},{"Series":"75´¢×79µ¡│","Population":[123,138,162,121,91,103,81]},{"Series":"80´¢×84µ¡│","Population":[145,93,105,126,94,72,82]},{"Series":"85´¢×89µ¡│","Population":[78,75,49,57,70,53,41]},{"Series":"90µ¡│õ╗Ñõ©è","Population":[35,40,42,33,34,41,35]}]