[{"Series":"þÀÅµò░","Population":[4392,3924,3483,3064,2663,2281,1937]},{"Series":"0´¢×4µ¡│","Population":[109,96,78,66,54,44,36]},{"Series":"5´¢×9µ¡│","Population":[108,107,96,77,65,53,43]},{"Series":"10´¢×14µ¡│","Population":[163,110,109,97,79,66,54]},{"Series":"15´¢×19µ¡│","Population":[158,130,88,87,78,63,53]},{"Series":"20´¢×24µ¡│","Population":[137,106,87,59,58,52,42]},{"Series":"25´¢×29µ¡│","Population":[155,147,112,91,61,60,53]},{"Series":"30´¢×34µ¡│","Population":[195,140,133,101,81,54,53]},{"Series":"35´¢×39µ¡│","Population":[213,169,122,116,87,70,47]},{"Series":"40´¢×44µ¡│","Population":[230,209,167,120,114,86,68]},{"Series":"45´¢×49µ¡│","Population":[263,228,208,166,119,113,85]},{"Series":"50´¢×54µ¡│","Population":[286,255,222,203,162,116,110]},{"Series":"55´¢×59µ¡│","Population":[319,283,253,220,202,161,116]},{"Series":"60´¢×64µ¡│","Population":[435,316,281,251,219,201,161]},{"Series":"65´¢×69µ¡│","Population":[493,423,309,275,246,214,198]},{"Series":"70´¢×74µ¡│","Population":[322,445,384,282,252,226,198]},{"Series":"75´¢×79µ¡│","Population":[338,274,384,332,246,221,199]},{"Series":"80´¢×84µ¡│","Population":[265,258,212,303,265,199,180]},{"Series":"85´¢×89µ¡│","Population":[154,157,156,131,194,173,132]},{"Series":"90µ¡│õ╗Ñõ©è","Population":[49,71,82,87,81,109,109]}]