[{"Series":"ГЇ▐Ф∙╟","Population":[970,831,716,619,525,441,362]},{"Series":"0ОҐ·4ФґЁ","Population":[15,17,14,12,9,6,5]},{"Series":"5ОҐ·9ФґЁ","Population":[20,14,16,13,11,9,7]},{"Series":"10ОҐ·14ФґЁ","Population":[35,18,13,15,12,10,8]},{"Series":"15ОҐ·19ФґЁ","Population":[23,16,9,6,7,5,5]},{"Series":"20ОҐ·24ФґЁ","Population":[15,16,12,7,4,5,4]},{"Series":"25ОҐ·29ФґЁ","Population":[33,17,20,14,8,5,5]},{"Series":"30ОҐ·34ФґЁ","Population":[26,30,17,19,13,7,5]},{"Series":"35ОҐ·39ФґЁ","Population":[32,24,27,15,17,13,7]},{"Series":"40ОҐ·44ФґЁ","Population":[37,32,24,27,16,18,12]},{"Series":"45ОҐ·49ФґЁ","Population":[33,36,30,23,26,14,17]},{"Series":"50ОҐ·54ФґЁ","Population":[56,33,34,29,22,26,14]},{"Series":"55ОҐ·59ФґЁ","Population":[80,54,31,34,29,22,25]},{"Series":"60ОҐ·64ФґЁ","Population":[87,76,52,30,32,27,20]},{"Series":"65ОҐ·69ФґЁ","Population":[88,85,75,51,30,32,27]},{"Series":"70ОҐ·74ФґЁ","Population":[69,84,81,72,49,29,31]},{"Series":"75ОҐ·79ФґЁ","Population":[92,64,78,76,67,46,27]},{"Series":"80ОҐ·84ФґЁ","Population":[93,78,55,68,65,58,40]},{"Series":"85ОҐ·89ФґЁ","Population":[86,68,58,42,52,50,45]},{"Series":"90ФґЁД╩╔Д╦┼","Population":[50,69,70,66,56,59,58]}]