[{"Series":"þÀÅµò░","Population":[3962,3291,2718,2236,1838,1489,1195]},{"Series":"0´¢×4µ¡│","Population":[64,53,39,31,22,16,12]},{"Series":"5´¢×9µ¡│","Population":[60,57,47,35,27,19,14]},{"Series":"10´¢×14µ¡│","Population":[64,54,51,42,31,24,17]},{"Series":"15´¢×19µ¡│","Population":[74,43,37,34,28,21,17]},{"Series":"20´¢×24µ¡│","Population":[60,41,24,21,20,16,12]},{"Series":"25´¢×29µ¡│","Population":[85,70,48,27,24,23,18]},{"Series":"30´¢×34µ¡│","Population":[115,82,67,47,28,24,24]},{"Series":"35´¢×39µ¡│","Population":[108,99,72,59,41,24,22]},{"Series":"40´¢×44µ¡│","Population":[126,104,95,70,56,41,23]},{"Series":"45´¢×49µ¡│","Population":[124,134,111,100,75,60,44]},{"Series":"50´¢×54µ¡│","Population":[211,124,134,111,101,74,61]},{"Series":"55´¢×59µ¡│","Population":[302,213,124,134,112,102,76]},{"Series":"60´¢×64µ¡│","Population":[354,296,209,121,133,111,101]},{"Series":"65´¢×69µ¡│","Population":[404,361,304,218,128,141,117]},{"Series":"70´¢×74µ¡│","Population":[372,372,332,281,202,118,131]},{"Series":"75´¢×79µ¡│","Population":[464,338,338,300,256,185,107]},{"Series":"80´¢×84µ¡│","Population":[467,366,269,271,243,207,152]},{"Series":"85´¢×89µ¡│","Population":[339,306,244,184,186,164,143]},{"Series":"90µ¡│õ╗Ñõ©è","Population":[169,178,173,150,125,119,104]}]