[{"code":"#G01101","name":"公民館数（人口100万人当たり）","unit":"館","year":"2021","value":"234.6","order":14},{"code":"#G01104","name":"図書館数（人口100万人当たり）","unit":"館","year":"2021","value":"61.7","order":2},{"code":"#G01107","name":"博物館数（人口100万人当たり）","unit":"館","year":"2021","value":"31.6","order":3},{"code":"#G01109","name":"青少年教育施設数（人口100万人当たり）","unit":"所","year":"2021","value":"12.0","order":9},{"code":"#G01321","name":"社会体育施設数（人口100万人当たり）","unit":"施設","year":"2021","value":"788.0","order":4},{"code":"#G01323","name":"多目的運動広場数（公共）（人口100万人当たり）","unit":"施設","year":"2021","value":"145.9","order":6},{"code":"#G01325","name":"体育館数（公共）（人口100万人当たり）","unit":"施設","year":"2021","value":"157.9","order":5},{"code":"#G01326","name":"水泳プール数（屋内，屋外）（公共）（人口100万人当たり）","unit":"施設","year":"2021","value":"52.6","order":3},{"code":"#G03201","name":"青少年学級・講座数（人口100万人当たり）","unit":"学級･講座","year":"2020","value":"2381.1","order":3},{"code":"#G03203","name":"成人一般学級・講座数（人口100万人当たり）","unit":"学級･講座","year":"2020","value":"5431.2","order":4},{"code":"#G0320501","name":"女性学級・講座数（女性人口100万人当たり）","unit":"学級･講座","year":"2020","value":"3148.5","order":1},{"code":"#G03207","name":"高齢者学級・講座数（人口100万人当たり）","unit":"学級･講座","year":"2020","value":"2378.1","order":1},{"code":"#G04101","name":"ボランティア活動の年間行動者率（15歳以上）","unit":"％","year":"2021","value":"26.1","order":1},{"code":"#G041011","name":"ボランティア活動の年間行動者率（10歳以上）","unit":"％","year":"2021","value":"25.6","order":1},{"code":"#G042111","name":"スポーツの年間行動者率（10歳以上）","unit":"％","year":"2021","value":"61.4","order":35},{"code":"#G0430501","name":"一般旅券発行件数（人口千人当たり）","unit":"件","year":"2024","value":"14.6","order":42},{"code":"#G04306","name":"旅行・行楽の年間行動者率（15歳以上）","unit":"％","year":"2001","value":"75.2","order":35},{"code":"#G043061","name":"旅行・行楽の年間行動者率（10歳以上）","unit":"％","year":"2021","value":"39.8","order":39},{"code":"#G04307","name":"海外旅行の年間行動者率（15歳以上）","unit":"％","year":"2001","value":"7.0","order":38},{"code":"#G043071","name":"海外旅行の年間行動者率（10歳以上）","unit":"％","year":"2021","value":"0.1","order":45},{"code":"#G04308","name":"客室稼働率","unit":"％","year":"2024","value":"68.6","order":13},{"code":"#G05102","name":"書籍・雑誌小売業年間商品販売額（人口1人当たり）","unit":"円","year":"2006","value":"12346","order":36}]