[{"code":"D110101","name":"市町村数","unit":"‐","year":"2024","value":"20","order":37},{"code":"D110102","name":"市区数","unit":"‐","year":"2024","value":"11","order":34},{"code":"D110103","name":"町村数","unit":"‐","year":"2024","value":"9","order":38},{"code":"D1201","name":"一般行政部門職員数（都道府県）","unit":"人","year":"2024","value":"3861","order":30},{"code":"D1202","name":"一般行政部門職員数（市区町村）","unit":"人","year":"2024","value":"8401","order":29},{"code":"D1203","name":"消防部門職員数","unit":"人","year":"2024","value":"1879","order":29},{"code":"D1204","name":"教育部門職員数","unit":"人","year":"2024","value":"12623","order":30},{"code":"D1205","name":"警察部門職員数","unit":"人","year":"2024","value":"2848","order":28},{"code":"D1206","name":"公営企業等会計部門職員数","unit":"人","year":"2024","value":"5380","order":24},{"code":"D1210","name":"都道府県議会議員数","unit":"人","year":"2024","value":"45","order":30},{"code":"D1211","name":"市区議会議員数","unit":"人","year":"2024","value":"254","order":33},{"code":"D1212","name":"選挙人名簿登録者数","unit":"人","year":"2024","value":"1108041","order":28},{"code":"D2101","name":"財政力指数（都道府県財政）","unit":"‐","year":"2022","value":"0.42197","order":28},{"code":"D2102","name":"実質収支比率（都道府県財政）","unit":"％","year":"2022","value":"1.6","order":37},{"code":"D2103","name":"経常収支比率（都道府県財政）","unit":"％","year":"2022","value":"87.6","order":45},{"code":"D2105","name":"基準財政収入額（都道府県財政）","unit":"千円","year":"2022","value":"141349735","order":27},{"code":"D2106","name":"基準財政需要額（都道府県財政）","unit":"千円","year":"2022","value":"322937643","order":30},{"code":"D2109","name":"一般財源（都道府県財政）","unit":"千円","year":"2022","value":"406269434","order":30},{"code":"D2110","name":"投資的経費（都道府県財政）","unit":"千円","year":"2022","value":"115513023","order":34},{"code":"D2111","name":"実質公債費比率（都道府県財政）","unit":"％","year":"2022","value":"11.1","order":22},{"code":"D2112","name":"将来負担比率（都道府県財政）","unit":"％","year":"2022","value":"124.4","order":37},{"code":"D2205","name":"基準財政収入額（市町村財政）","unit":"千円","year":"2022","value":"177176079","order":28},{"code":"D2206","name":"基準財政需要額（市町村財政）","unit":"千円","year":"2022","value":"324314786","order":28},{"code":"D2209","name":"一般財源（市町村財政）","unit":"千円","year":"2022","value":"359445850","order":29},{"code":"D2210","name":"投資的経費（市町村財政）","unit":"千円","year":"2022","value":"76555470","order":34},{"code":"D3101","name":"歳入決算総額（都道府県財政）","unit":"千円","year":"2022","value":"734178021","order":31},{"code":"D310101","name":"地方税（都道府県財政）","unit":"千円","year":"2022","value":"192499721","order":27},{"code":"D310102","name":"地方譲与税（都道府県財政）","unit":"千円","year":"2022","value":"27850750","order":28},{"code":"D310103","name":"地方交付税（都道府県財政）","unit":"千円","year":"2022","value":"185084137","order":28},{"code":"D310104","name":"交通安全対策特別交付金（都道府県財政）","unit":"千円","year":"2022","value":"280291","order":35},{"code":"D310105","name":"分担金及び負担金（都道府県財政）","unit":"千円","year":"2022","value":"4612489","order":18},{"code":"D310106","name":"使用料（都道府県財政）","unit":"千円","year":"2022","value":"5470972","order":33},{"code":"D310107","name":"手数料（都道府県財政）","unit":"千円","year":"2022","value":"1790409","order":34},{"code":"D310108","name":"国庫支出金（都道府県財政）","unit":"千円","year":"2022","value":"145501027","order":34},{"code":"D310110","name":"財産収入（都道府県財政）","unit":"千円","year":"2022","value":"1381777","order":36},{"code":"D310111","name":"寄附金（都道府県財政）","unit":"千円","year":"2022","value":"206390","order":31},{"code":"D310112","name":"繰入金（都道府県財政）","unit":"千円","year":"2022","value":"12278943","order":31},{"code":"D310113","name":"繰越金（都道府県財政）","unit":"千円","year":"2022","value":"19071498","order":33},{"code":"D310114","name":"諸収入（都道府県財政）","unit":"千円","year":"2022","value":"84010791","order":22},{"code":"D310115","name":"地方債（都道府県財政）","unit":"千円","year":"2022","value":"53304000","order":38},{"code":"D310116","name":"地方特例交付金（都道府県財政）","unit":"千円","year":"2022","value":"834826","order":29},{"code":"D3102","name":"自主財源額（都道府県財政）","unit":"千円","year":"2022","value":"321322990","order":27},{"code":"D3103","name":"歳出決算総額（都道府県財政）","unit":"千円","year":"2022","value":"707431134","order":30},{"code":"D310301","name":"議会費（都道府県財政）","unit":"千円","year":"2022","value":"1195976","order":31},{"code":"D310302","name":"総務費（都道府県財政）","unit":"千円","year":"2022","value":"38950176","order":34},{"code":"D310303","name":"民生費（都道府県財政）","unit":"千円","year":"2022","value":"105873364","order":28},{"code":"D3103031","name":"社会福祉費（都道府県財政）","unit":"千円","year":"2022","value":"33707710","order":27},{"code":"D3103032","name":"老人福祉費（都道府県財政）","unit":"千円","year":"2022","value":"47800106","order":26},{"code":"D3103033","name":"児童福祉費（都道府県財政）","unit":"千円","year":"2022","value":"21061382","order":35},{"code":"D3103034","name":"生活保護費（都道府県財政）","unit":"千円","year":"2022","value":"3288477","order":23},{"code":"D3103035","name":"災害救助費（都道府県財政）","unit":"千円","year":"2022","value":"15689","order":36},{"code":"D310304","name":"衛生費（都道府県財政）","unit":"千円","year":"2022","value":"58747654","order":33},{"code":"D3103041","name":"公衆衛生費（都道府県財政）","unit":"千円","year":"2022","value":"30916235","order":32},{"code":"D3103043","name":"精神衛生費（都道府県財政）","unit":"千円","year":"2022","value":"305022","order":35},{"code":"D3103044","name":"環境衛生費（都道府県財政）","unit":"千円","year":"2022","value":"3356659","order":32},{"code":"D3103045","name":"清掃費（都道府県財政）","unit":"千円","year":"2022","value":"0","order":34},{"code":"D3103046","name":"保健所費（都道府県財政）","unit":"千円","year":"2022","value":"1702383","order":27},{"code":"D310305","name":"労働費（都道府県財政）","unit":"千円","year":"2022","value":"2016353","order":26},{"code":"D3103051","name":"労政費（都道府県財政）","unit":"千円","year":"2022","value":"545409","order":22},{"code":"D3103052","name":"職業訓練費（都道府県財政）","unit":"千円","year":"2022","value":"1390950","order":21},{"code":"D3103053","name":"失業対策費（都道府県財政）","unit":"千円","year":"2022","value":"0","order":16},{"code":"D310306","name":"農林水産業費（都道府県財政）","unit":"千円","year":"2022","value":"39627765","order":28},{"code":"D310307","name":"商工費（都道府県財政）","unit":"千円","year":"2022","value":"87905122","order":27},{"code":"D310308","name":"土木費（都道府県財政）","unit":"千円","year":"2022","value":"87477101","order":29},{"code":"D3103082","name":"道路橋りょう費（都道府県財政）","unit":"千円","year":"2022","value":"37934985","order":35},{"code":"D3103085","name":"都市計画費（都道府県財政）","unit":"千円","year":"2022","value":"8675911","order":24},{"code":"D3103086","name":"住宅費（都道府県財政）","unit":"千円","year":"2022","value":"803491","order":46},{"code":"D310309","name":"警察費（都道府県財政）","unit":"千円","year":"2022","value":"32395913","order":28},{"code":"D310310","name":"消防費（都道府県財政）","unit":"千円","year":"2022","value":"0","order":2},{"code":"D310311","name":"教育費（都道府県財政）","unit":"千円","year":"2022","value":"128400087","order":31},{"code":"D3103112","name":"小学校費（都道府県財政）","unit":"千円","year":"2022","value":"37235332","order":27},{"code":"D3103113","name":"中学校費（都道府県財政）","unit":"千円","year":"2022","value":"22148065","order":28},{"code":"D3103114","name":"高等学校費（都道府県財政）","unit":"千円","year":"2022","value":"30448727","order":27},{"code":"D3103115","name":"特別支援学校費（都道府県財政）","unit":"千円","year":"2022","value":"8934257","order":37},{"code":"D3103116","name":"幼稚園費（都道府県財政）","unit":"千円","year":"2022","value":"0","order":16},{"code":"D3103117","name":"社会教育費（都道府県財政）","unit":"千円","year":"2022","value":"3492007","order":20},{"code":"D3103118","name":"保健体育費（都道府県財政）","unit":"千円","year":"2022","value":"1971627","order":22},{"code":"D310312","name":"災害復旧費（都道府県財政）","unit":"千円","year":"2022","value":"5544232","order":19},{"code":"D310313","name":"公債費（都道府県財政）（目的別歳出内訳）","unit":"千円","year":"2022","value":"80772481","order":36},{"code":"D310401","name":"人件費（都道府県財政）","unit":"千円","year":"2022","value":"162201867","order":30},{"code":"D310402","name":"物件費（都道府県財政）","unit":"千円","year":"2022","value":"34131858","order":38},{"code":"D310403","name":"維持補修費（都道府県財政）","unit":"千円","year":"2022","value":"3965632","order":41},{"code":"D310404","name":"扶助費（都道府県財政）","unit":"千円","year":"2022","value":"30604633","order":13},{"code":"D310405","name":"補助費等（都道府県財政）","unit":"千円","year":"2022","value":"184015412","order":34},{"code":"D310406","name":"普通建設事業費（都道府県財政）","unit":"千円","year":"2022","value":"109971455","order":35},{"code":"D310407","name":"災害復旧事業費（都道府県財政）","unit":"千円","year":"2022","value":"5541568","order":19},{"code":"D310408","name":"失業対策事業費（都道府県財政）","unit":"千円","year":"2022","value":"0","order":1},{"code":"D310409","name":"公債費（都道府県財政）（性質別歳出内訳）","unit":"千円","year":"2022","value":"80750677","order":36},{"code":"D310410","name":"積立金（都道府県財政）","unit":"千円","year":"2022","value":"13937111","order":36},{"code":"D310411","name":"投資及び出資金（都道府県財政）","unit":"千円","year":"2022","value":"0","order":35},{"code":"D310412","name":"貸付金（都道府県財政）","unit":"千円","year":"2022","value":"74506025","order":21},{"code":"D3105","name":"地方債現在高（都道府県財政）","unit":"千円","year":"2022","value":"994691862","order":35},{"code":"D3201","name":"歳入決算総額（市町村財政）","unit":"千円","year":"2022","value":"756348323","order":29},{"code":"D320101","name":"地方税（市町村財政）","unit":"千円","year":"2022","value":"186929237","order":28},{"code":"D320102","name":"地方譲与税（市町村財政）","unit":"千円","year":"2022","value":"5939679","order":30},{"code":"D320103","name":"利子割交付金（市町村財政）","unit":"千円","year":"2022","value":"145021","order":13},{"code":"D320104","name":"ゴルフ場利用税交付金（市町村財政）","unit":"千円","year":"2022","value":"247284","order":32},{"code":"D320105","name":"特別地方消費税交付金（市町村財政）","unit":"千円","year":"2022","value":"0","order":1},{"code":"D320106","name":"自動車取得税交付金（市町村財政）","unit":"千円","year":"2022","value":"0","order":34},{"code":"D320107","name":"軽油引取税交付金（市町村財政）","unit":"千円","year":"2022","value":"0","order":16},{"code":"D320108","name":"地方交付税（市町村財政）","unit":"千円","year":"2022","value":"165230250","order":23},{"code":"D320109","name":"交通安全対策特別交付金（市町村財政）","unit":"千円","year":"2022","value":"139692","order":34},{"code":"D320110","name":"分担金及び負担金（市町村財政）","unit":"千円","year":"2022","value":"17167943","order":43},{"code":"D320111","name":"使用料（市町村財政）","unit":"千円","year":"2022","value":"7294073","order":28},{"code":"D320113","name":"国庫支出金（市町村財政）","unit":"千円","year":"2022","value":"139779284","order":28},{"code":"D320115","name":"県支出金（市町村財政）","unit":"千円","year":"2022","value":"53248772","order":30},{"code":"D320116","name":"財産収入（市町村財政）","unit":"千円","year":"2022","value":"1708101","order":43},{"code":"D320117","name":"寄附金（市町村財政）","unit":"千円","year":"2022","value":"9471773","order":33},{"code":"D320118","name":"繰入金（市町村財政）","unit":"千円","year":"2022","value":"20260298","order":37},{"code":"D320119","name":"繰越金（市町村財政）","unit":"千円","year":"2022","value":"38923036","order":24},{"code":"D320120","name":"諸収入（市町村財政）","unit":"千円","year":"2022","value":"22592057","order":26},{"code":"D320121","name":"地方債（市町村財政）","unit":"千円","year":"2022","value":"44585654","order":31},{"code":"D320122","name":"地方特例交付金（市町村財政）","unit":"千円","year":"2022","value":"1346684","order":29},{"code":"D320123","name":"地方消費税交付金（市町村財政）","unit":"千円","year":"2022","value":"33034406","order":28},{"code":"D320124","name":"自動車税環境性能割交付金（市町村財政）","unit":"千円","year":"2022","value":"395342","order":32},{"code":"D3202","name":"自主財源額（市町村財政）","unit":"千円","year":"2022","value":"307552453","order":30},{"code":"D3203","name":"歳出決算総額（市町村財政）","unit":"千円","year":"2022","value":"718488329","order":30},{"code":"D3203001","name":"歳出決算総額（市町村財政・東京都分含む）","unit":"千円","year":"2022","value":"0","order":2},{"code":"D320301","name":"議会費（市町村財政）","unit":"千円","year":"2022","value":"3765990","order":33},{"code":"D320302","name":"総務費（市町村財政）","unit":"千円","year":"2022","value":"94782030","order":35},{"code":"D320303","name":"民生費（市町村財政）","unit":"千円","year":"2022","value":"266965291","order":27},{"code":"D3203031","name":"社会福祉費（市町村財政）","unit":"千円","year":"2022","value":"89457072","order":26},{"code":"D3203032","name":"老人福祉費（市町村財政）","unit":"千円","year":"2022","value":"56187337","order":24},{"code":"D3203033","name":"児童福祉費（市町村財政）","unit":"千円","year":"2022","value":"87369859","order":31},{"code":"D3203034","name":"生活保護費（市町村財政）","unit":"千円","year":"2022","value":"33944611","order":22},{"code":"D3203035","name":"災害救助費（市町村財政）","unit":"千円","year":"2022","value":"6412","order":40},{"code":"D320304","name":"衛生費（市町村財政）","unit":"千円","year":"2022","value":"69665804","order":33},{"code":"D3203042","name":"保健衛生費（市町村財政）","unit":"千円","year":"2022","value":"40395546","order":31},{"code":"D3203043","name":"保健所費（市町村財政）","unit":"千円","year":"2022","value":"1691331","order":18},{"code":"D3203044","name":"清掃費（市町村財政）","unit":"千円","year":"2022","value":"27538073","order":36},{"code":"D320305","name":"労働費（市町村財政）","unit":"千円","year":"2022","value":"1646588","order":15},{"code":"D3203051","name":"失業対策費（市町村財政）","unit":"千円","year":"2022","value":"100000","order":2},{"code":"D320306","name":"農林水産業費（市町村財政）","unit":"千円","year":"2022","value":"25070312","order":26},{"code":"D320307","name":"商工費（市町村財政）","unit":"千円","year":"2022","value":"27210713","order":30},{"code":"D320308","name":"土木費（市町村財政）","unit":"千円","year":"2022","value":"58358774","order":34},{"code":"D3203082","name":"道路橋りょう費（市町村財政）","unit":"千円","year":"2022","value":"16608738","order":37},{"code":"D3203085","name":"都市計画費（市町村財政）","unit":"千円","year":"2022","value":"27444372","order":32},{"code":"D3203086","name":"住宅費（市町村財政）","unit":"千円","year":"2022","value":"5175950","order":28},{"code":"D320309","name":"消防費（市町村財政）","unit":"千円","year":"2022","value":"27521748","order":32},{"code":"D3203099","name":"消防費（東京都・市町村財政合計）","unit":"千円","year":"2022","value":"27521748","order":32},{"code":"D320310","name":"教育費（市町村財政）","unit":"千円","year":"2022","value":"66290085","order":31},{"code":"D3203102","name":"小学校費（市町村財政）","unit":"千円","year":"2022","value":"14334240","order":31},{"code":"D3203103","name":"中学校費（市町村財政）","unit":"千円","year":"2022","value":"8024880","order":32},{"code":"D3203104","name":"高等学校費（市町村財政）","unit":"千円","year":"2022","value":"36180","order":36},{"code":"D3203105","name":"特別支援学校費（市町村財政）","unit":"千円","year":"2022","value":"0","order":29},{"code":"D3203106","name":"幼稚園費（市町村財政）","unit":"千円","year":"2022","value":"2083079","order":31},{"code":"D3203107","name":"社会教育費（市町村財政）","unit":"千円","year":"2022","value":"13323051","order":31},{"code":"D3203108","name":"保健体育費（市町村財政）","unit":"千円","year":"2022","value":"16144261","order":28},{"code":"D320311","name":"災害復旧費（市町村財政）","unit":"千円","year":"2022","value":"5323510","order":18},{"code":"D320312","name":"公債費（市町村財政）（目的別歳出内訳）","unit":"千円","year":"2022","value":"71682259","order":28},{"code":"D320401","name":"人件費（市町村財政）","unit":"千円","year":"2022","value":"115614903","order":30},{"code":"D320402","name":"物件費（市町村財政）","unit":"千円","year":"2022","value":"98111080","order":34},{"code":"D320403","name":"維持補修費（市町村財政）","unit":"千円","year":"2022","value":"5911973","order":36},{"code":"D320404","name":"扶助費（市町村財政）","unit":"千円","year":"2022","value":"159092276","order":29},{"code":"D320405","name":"補助費等（市町村財政）","unit":"千円","year":"2022","value":"84004043","order":32},{"code":"D320406","name":"普通建設事業費（市町村財政）","unit":"千円","year":"2022","value":"71234487","order":34},{"code":"D320407","name":"災害復旧事業費（市町村財政）","unit":"千円","year":"2022","value":"5320983","order":18},{"code":"D320408","name":"失業対策事業費（市町村財政）","unit":"千円","year":"2022","value":"0","order":2},{"code":"D320409","name":"公債費（市町村財政）（性質別歳出内訳）","unit":"千円","year":"2022","value":"71681587","order":28},{"code":"D320410","name":"積立金（市町村財政）","unit":"千円","year":"2022","value":"27475506","order":35},{"code":"D320411","name":"投資及び出資金（市町村財政）","unit":"千円","year":"2022","value":"5550165","order":20},{"code":"D320412","name":"貸付金（市町村財政）","unit":"千円","year":"2022","value":"8085864","order":23},{"code":"D3205","name":"地方債現在高（市町村財政）","unit":"千円","year":"2022","value":"643107636","order":29},{"code":"D4101","name":"普通税（地方税）","unit":"千円","year":"2022","value":"375699439","order":28},{"code":"D410101","name":"普通税（都道府県税）","unit":"千円","year":"2022","value":"192244297","order":27},{"code":"D410102","name":"普通税（市町村税）","unit":"千円","year":"2022","value":"183455142","order":28},{"code":"D4102","name":"目的税（地方税）","unit":"千円","year":"2022","value":"3729519","order":36},{"code":"D410201","name":"目的税（都道府県税）","unit":"千円","year":"2022","value":"255424","order":13},{"code":"D410202","name":"目的税（市町村税）","unit":"千円","year":"2022","value":"3474095","order":36},{"code":"D4201","name":"住民税（都道府県，市町村財政合計）","unit":"千円","year":"2022","value":"125586370","order":29},{"code":"D420101","name":"都道府県民税","unit":"千円","year":"2022","value":"47963444","order":27},{"code":"D420102","name":"市町村民税","unit":"千円","year":"2022","value":"77622926","order":29},{"code":"D4202","name":"固定資産税（都道府県，市町村財政合計）","unit":"千円","year":"2022","value":"91098626","order":28},{"code":"D420201","name":"固定資産税（都道府県税）","unit":"千円","year":"2022","value":"0","order":5},{"code":"D420202","name":"固定資産税（市町村税）","unit":"千円","year":"2022","value":"91098626","order":28},{"code":"D4203","name":"事業税","unit":"千円","year":"2022","value":"44410262","order":26},{"code":"D430101","name":"国税徴収決定済額","unit":"百万円","year":"2023","value":"574825","order":24},{"code":"D430102","name":"都道府県税徴収決定済額","unit":"千円","year":"2022","value":"168156394","order":26},{"code":"D430103","name":"市町村税徴収決定済額","unit":"千円","year":"2018","value":"187615687","order":28},{"code":"D4302","name":"収納済額","unit":"百万円","year":"2018","value":"804638","order":24},{"code":"D430201","name":"国税収納済額","unit":"百万円","year":"2023","value":"560844","order":24},{"code":"D430202","name":"都道府県税収納済額","unit":"千円","year":"2022","value":"167380114","order":26},{"code":"D430203","name":"市町村税収納済額","unit":"千円","year":"2018","value":"183393825","order":27},{"code":"D5100","name":"行政総投資額","unit":"千円","year":"2022","value":"277670297","order":39},{"code":"D5200","name":"一般事業総投資額","unit":"千円","year":"2022","value":"240866246","order":39},{"code":"D5201","name":"一般事業投資額（道路）","unit":"千円","year":"2006","value":"108158628","order":19},{"code":"D5202","name":"一般事業投資額（農林水産）","unit":"千円","year":"2006","value":"34990090","order":25},{"code":"D5203","name":"一般事業投資額（住宅）","unit":"千円","year":"2006","value":"4786825","order":33},{"code":"D5204","name":"一般事業投資額（環境衛生）","unit":"千円","year":"2006","value":"5442519","order":38},{"code":"D5205","name":"一般事業投資額（厚生福祉）","unit":"千円","year":"2006","value":"6808398","order":32},{"code":"D5206","name":"一般事業投資額（治山治水）","unit":"千円","year":"2006","value":"30278593","order":35},{"code":"D5207","name":"一般事業投資額（都市計画）","unit":"千円","year":"2006","value":"10812312","order":32},{"code":"D5208","name":"一般事業投資額（文教施設）","unit":"千円","year":"2006","value":"15879082","order":42},{"code":"D5210","name":"一般事業投資額（災害復旧）","unit":"千円","year":"2006","value":"9754842","order":18},{"code":"D5211","name":"一般事業投資額（鉄道）","unit":"千円","year":"2006","value":"0","order":26},{"code":"D5300","name":"公営企業総投資額","unit":"千円","year":"2022","value":"36739118","order":31}]