[{"code":"#M01101","name":"1次活動の平均時間（男）","unit":"分","year":"2021","value":"655","order":18},{"code":"#M01102","name":"1次活動の平均時間（女）","unit":"分","year":"2021","value":"652","order":46},{"code":"#M0120106","name":"2次活動の平均時間（有業者・男）","unit":"分","year":"2021","value":"496","order":8},{"code":"#M0120107","name":"2次活動の平均時間（無業者・男）","unit":"分","year":"2021","value":"151","order":40},{"code":"#M0120206","name":"2次活動の平均時間（有業者・女）","unit":"分","year":"2021","value":"546","order":1},{"code":"#M0120207","name":"2次活動の平均時間（無業者・女）","unit":"分","year":"2021","value":"292","order":26},{"code":"#M0130106","name":"3次活動の平均時間（有業者・男）","unit":"分","year":"2021","value":"308","order":45},{"code":"#M0130107","name":"3次活動の平均時間（無業者・男）","unit":"分","year":"2021","value":"589","order":9},{"code":"#M0130206","name":"3次活動の平均時間（有業者・女）","unit":"分","year":"2021","value":"272","order":39},{"code":"#M0130207","name":"3次活動の平均時間（無業者・女）","unit":"分","year":"2021","value":"460","order":12},{"code":"#M0210101","name":"仕事の平均時間（有業者・男）","unit":"分","year":"2021","value":"406","order":1},{"code":"#M0210201","name":"仕事の平均時間（有業者・女）","unit":"分","year":"2021","value":"302","order":9},{"code":"#M0310101","name":"趣味・娯楽の平均時間（有業者・男）","unit":"分","year":"2021","value":"43","order":34},{"code":"#M0310102","name":"趣味・娯楽の平均時間（無業者・男）","unit":"分","year":"2021","value":"75","order":28},{"code":"#M0310201","name":"趣味・娯楽の平均時間（有業者・女）","unit":"分","year":"2021","value":"26","order":30},{"code":"#M0310202","name":"趣味・娯楽の平均時間（無業者・女）","unit":"分","year":"2021","value":"37","order":35},{"code":"#M0330101","name":"テレビ・ラジオ・新聞・雑誌の平均時間（有業者・男）","unit":"分","year":"2021","value":"99","order":21},{"code":"#M0330102","name":"テレビ・ラジオ・新聞・雑誌の平均時間（無業者・男）","unit":"分","year":"2021","value":"264","order":7},{"code":"#M0330201","name":"テレビ・ラジオ・新聞・雑誌の平均時間（有業者・女）","unit":"分","year":"2021","value":"89","order":16},{"code":"#M0330202","name":"テレビ・ラジオ・新聞・雑誌の平均時間（無業者・女）","unit":"分","year":"2021","value":"192","order":21}]