[{"code":"J1101","name":"生活保護被保護実世帯数","unit":"世帯","year":"2023","value":"19519","order":19},{"code":"J1102","name":"現に保護を受けた生活保護被保護実世帯数","unit":"世帯","year":"2023","value":"19416","order":19},{"code":"J110201","name":"現に保護を受けた生活保護被保護実世帯数（母子世帯）","unit":"世帯","year":"2023","value":"667","order":19},{"code":"J110202","name":"現に保護を受けた生活保護被保護実世帯数（傷病・障害者世帯）","unit":"世帯","year":"2023","value":"4078","order":22},{"code":"J110203","name":"現に保護を受けた生活保護被保護実世帯数（高齢者世帯）","unit":"世帯","year":"2023","value":"11449","order":19},{"code":"J110204","name":"現に保護を受けた医療扶助単給世帯数","unit":"世帯","year":"2023","value":"938","order":15},{"code":"J1103","name":"保護開始世帯数","unit":"世帯","year":"2023","value":"252","order":16},{"code":"J110301","name":"保護開始世帯数（母子世帯）","unit":"世帯","year":"2023","value":"9","order":18},{"code":"J110302","name":"保護開始世帯数（高齢者世帯）","unit":"世帯","year":"2023","value":"92","order":17},{"code":"J110303","name":"保護開始世帯数（その他の世帯）","unit":"世帯","year":"2023","value":"103","order":18},{"code":"J1104","name":"生活保護扶助世帯数","unit":"世帯","year":"2023","value":"55743","order":19},{"code":"J110401","name":"生活保護扶助世帯数（生活）","unit":"世帯","year":"2023","value":"17147","order":19},{"code":"J110402","name":"生活保護扶助世帯数（住宅）","unit":"世帯","year":"2023","value":"15768","order":19},{"code":"J110403","name":"生活保護扶助世帯数（教育）","unit":"世帯","year":"2023","value":"612","order":19},{"code":"J110404","name":"生活保護扶助世帯数（医療）","unit":"世帯","year":"2023","value":"16863","order":20},{"code":"J1104041","name":"生活保護扶助世帯数（介護）","unit":"世帯","year":"2023","value":"5023","order":18},{"code":"J110405","name":"生活保護扶助世帯数（出産）","unit":"世帯","year":"2023","value":"1","order":20},{"code":"J110406","name":"生活保護扶助世帯数（生業）","unit":"世帯","year":"2023","value":"290","order":21},{"code":"J110407","name":"生活保護扶助世帯数（葬祭）","unit":"世帯","year":"2023","value":"39","order":17},{"code":"J1105","name":"生活保護被保護実人員","unit":"人","year":"2023","value":"23881","order":19},{"code":"J1106","name":"生活保護扶助人員","unit":"人","year":"2023","value":"66270","order":20},{"code":"J110601","name":"生活保護扶助人員（生活）","unit":"人","year":"2023","value":"20967","order":19},{"code":"J110602","name":"生活保護扶助人員（住宅）","unit":"人","year":"2023","value":"19405","order":20},{"code":"J110603","name":"生活保護扶助人員（教育）","unit":"人","year":"2023","value":"969","order":18},{"code":"J110604","name":"生活保護扶助人員（医療）","unit":"人","year":"2023","value":"19445","order":20},{"code":"J1106041","name":"生活保護扶助人員（介護）","unit":"人","year":"2023","value":"5111","order":18},{"code":"J110605","name":"生活保護扶助人員（出産）","unit":"人","year":"2023","value":"1","order":20},{"code":"J110606","name":"生活保護扶助人員（生業）","unit":"人","year":"2023","value":"333","order":21},{"code":"J110607","name":"生活保護扶助人員（葬祭）","unit":"人","year":"2023","value":"39","order":17},{"code":"J110702","name":"生活保護被保護高齢者数（65歳以上）","unit":"人","year":"2022","value":"12998","order":19},{"code":"J110703","name":"教育扶助受給人員、小－中学校","unit":"人","year":"2022","value":"1036","order":18},{"code":"J110704","name":"高等学校等就学費受給人員","unit":"人","year":"2022","value":"348","order":20},{"code":"J1200","name":"身体障害者手帳交付数","unit":"人","year":"2023","value":"79477","order":16},{"code":"J120001","name":"身体障害者手帳交付数（18歳以上）","unit":"人","year":"2007","value":"92653","order":16},{"code":"J120002","name":"身体障害者手帳交付数（18歳未満）","unit":"人","year":"2007","value":"1203","order":27},{"code":"J1201","name":"身体障害者手帳交付数（視覚障害）","unit":"人","year":"2007","value":"8070","order":14},{"code":"J120101","name":"身体障害者手帳交付数（視覚障害）（18歳以上）","unit":"人","year":"2007","value":"8029","order":14},{"code":"J120102","name":"身体障害者手帳交付数（視覚障害）（18歳未満）","unit":"人","year":"2007","value":"41","order":32},{"code":"J1202","name":"身体障害者手帳交付数（聴覚・平衡機能障害）","unit":"人","year":"2007","value":"9017","order":14},{"code":"J120201","name":"身体障害者手帳交付数（聴覚・平衡機能障害）（18歳以上）","unit":"人","year":"2007","value":"8818","order":14},{"code":"J120202","name":"身体障害者手帳交付数（聴覚・平衡機能障害）（18歳未満）","unit":"人","year":"2007","value":"199","order":25},{"code":"J1203","name":"身体障害者手帳交付数（音声・言語・そしゃく機能障害）","unit":"人","year":"2007","value":"858","order":21},{"code":"J120301","name":"身体障害者手帳交付数（音声・言語・そしゃく機能障害）（18歳以上）","unit":"人","year":"2007","value":"850","order":21},{"code":"J120302","name":"身体障害者手帳交付数（音声・言語・そしゃく機能障害）（18歳未満）","unit":"人","year":"2007","value":"8","order":25},{"code":"J1204","name":"身体障害者手帳交付数（肢体不自由障害）","unit":"人","year":"2007","value":"46789","order":20},{"code":"J120401","name":"身体障害者手帳交付数（肢体不自由障害）（18歳以上）","unit":"人","year":"2007","value":"45996","order":20},{"code":"J120402","name":"身体障害者手帳交付数（肢体不自由障害）（18歳未満）","unit":"人","year":"2007","value":"793","order":24},{"code":"J1205","name":"身体障害者手帳交付数（内部障害）","unit":"人","year":"2007","value":"29122","order":13},{"code":"J120501","name":"身体障害者手帳交付数（内部障害）（18歳以上）","unit":"人","year":"2007","value":"28960","order":13},{"code":"J120502","name":"身体障害者手帳交付数（内部障害）（18歳未満）","unit":"人","year":"2007","value":"162","order":37},{"code":"J1210","name":"身体障害者補装具交付決定件数","unit":"件","year":"2007","value":"2693","order":16},{"code":"J1212","name":"身体障害者補装具修理決定件数","unit":"件","year":"2007","value":"1655","order":18},{"code":"J1213","name":"身体障害者補装具修理負担額","unit":"円","year":"2007","value":"76929000","order":18},{"code":"J121301","name":"身体障害者補装具修理負担額（公費負担額）","unit":"円","year":"2007","value":"70106000","order":18},{"code":"J1301","name":"精神障害者保健福祉手帳交付件数","unit":"件","year":"2023","value":"22493","order":17},{"code":"J130101","name":"精神障害保健福祉手帳交付件数（1級）","unit":"件","year":"2007","value":"3828","order":7},{"code":"J130102","name":"精神障害保健福祉手帳交付件数（2級）","unit":"件","year":"2007","value":"6012","order":16},{"code":"J130103","name":"精神障害保健福祉手帳交付件数（3級）","unit":"件","year":"2007","value":"456","order":44},{"code":"J1401","name":"児童扶養手当受給者数","unit":"人","year":"2023","value":"15322","order":15},{"code":"J1501","name":"知的障害者療育手帳交付数","unit":"人","year":"2023","value":"22599","order":16},{"code":"J2101","name":"社会福祉施設数","unit":"所","year":"2007","value":"1316","order":15},{"code":"J2103","name":"社会福祉施設従事者数（常勤）","unit":"人","year":"2007","value":"14831","order":14},{"code":"J2201","name":"保護施設数（詳細票）（医療保護施設を除く）","unit":"所","year":"2023","value":"7","order":9},{"code":"J2202","name":"保護施設定員数（医療保護施設を含む）","unit":"人","year":"2002","value":"417","order":29},{"code":"J2203","name":"保護施設定員数（詳細票）（医療保護施設を除く）","unit":"人","year":"2023","value":"380","order":15},{"code":"J2205","name":"保護施設在所者数（医療保護施設を含む）","unit":"人","year":"2002","value":"429","order":28},{"code":"J2206","name":"保護施設在所者数（詳細票）（医療保護施設を除く）","unit":"人","year":"2023","value":"400","order":14},{"code":"J2209","name":"保護施設従事者数（医療保護施設を除く）（専任）","unit":"人","year":"2001","value":"139","order":13},{"code":"J2212","name":"保護施設従事者数（詳細票）（医療保護施設を除く）（常勤）","unit":"人","year":"2023","value":"145","order":13},{"code":"J2221","name":"保護施設数（基本票）（医療保護施設を除く）","unit":"所","year":"2023","value":"7","order":9},{"code":"J2300","name":"老人福祉関係施設数","unit":"所","year":"2007","value":"328","order":11},{"code":"J2301","name":"老人福祉施設数（詳細票）","unit":"所","year":"2023","value":"71","order":17},{"code":"J230111","name":"養護老人ホーム数（詳細票）","unit":"所","year":"2023","value":"35","order":5},{"code":"J230112","name":"養護老人ホーム定員数（詳細票）","unit":"人","year":"2023","value":"1840","order":9},{"code":"J230113","name":"養護老人ホーム在所者数（詳細票）","unit":"人","year":"2023","value":"1680","order":9},{"code":"J230115","name":"養護老人ホーム従事者数（詳細票）（常勤）","unit":"人","year":"2023","value":"506","order":7},{"code":"J230121","name":"介護老人福祉施設数（詳細票）","unit":"所","year":"2023","value":"139","order":24},{"code":"J230124","name":"介護老人福祉施設定員数（詳細票）","unit":"人","year":"2023","value":"7438","order":28},{"code":"J230125","name":"介護老人福祉施設在所者数（詳細票）","unit":"人","year":"2023","value":"7158","order":27},{"code":"J230126","name":"介護老人福祉施設従事者数（詳細票）","unit":"人","year":"2023","value":"5190","order":26},{"code":"J230127","name":"介護老人福祉施設数（基本票）","unit":"所","year":"2023","value":"139","order":24},{"code":"J230128","name":"介護老人福祉施設定員数（基本票）","unit":"人","year":"2023","value":"7527","order":26},{"code":"J230131","name":"軽費老人ホーム数（詳細票）","unit":"所","year":"2023","value":"36","order":28},{"code":"J230132","name":"軽費老人ホーム定員数（詳細票）","unit":"人","year":"2023","value":"1528","order":23},{"code":"J230133","name":"軽費老人ホーム在所者数（詳細票）","unit":"人","year":"2023","value":"1440","order":21},{"code":"J230135","name":"軽費老人ホーム従事者数（詳細票）（常勤）","unit":"人","year":"2023","value":"296","order":29},{"code":"J230141","name":"老人福祉センター数","unit":"所","year":"2017","value":"43","order":15},{"code":"J230144","name":"老人福祉センター従事者数（専任）","unit":"人","year":"2001","value":"95","order":30},{"code":"J230145","name":"老人福祉センター従事者数（常勤）","unit":"人","year":"2017","value":"95","order":24},{"code":"J230155","name":"訪問介護事業所数","unit":"所","year":"2023","value":"625","order":13},{"code":"J230156","name":"訪問介護利用者数","unit":"人","year":"2023","value":"25201","order":12},{"code":"J230162","name":"訪問入浴介護事業所数","unit":"所","year":"2023","value":"21","order":26},{"code":"J230163","name":"訪問入浴介護利用者数","unit":"人","year":"2021","value":"446","order":34},{"code":"J230165","name":"通所介護事業所数","unit":"所","year":"2023","value":"459","order":18},{"code":"J230166","name":"通所介護定員数","unit":"人","year":"2021","value":"14052","order":20},{"code":"J230167","name":"通所介護従事者数","unit":"人","year":"2023","value":"5469","order":16},{"code":"J230168","name":"通所介護利用者数","unit":"人","year":"2021","value":"20410","order":23},{"code":"J230171","name":"短期入所生活介護事業所数","unit":"所","year":"2023","value":"188","order":27},{"code":"J230172","name":"短期入所生活介護定員数","unit":"人","year":"2021","value":"1907","order":31},{"code":"J230173","name":"短期入所生活介護従事者数","unit":"人","year":"2023","value":"3990","order":24},{"code":"J230174","name":"短期入所生活介護利用者数","unit":"人","year":"2021","value":"3372","order":30},{"code":"J230181","name":"居宅介護支援事業所数","unit":"所","year":"2023","value":"715","order":15},{"code":"J230182","name":"居宅介護支援事業利用者数","unit":"人","year":"2023","value":"44575","order":21},{"code":"J230191","name":"老人介護支援センター数","unit":"所","year":"2009","value":"38","order":36},{"code":"J2302","name":"その他の老人福祉施設数","unit":"所","year":"2007","value":"237","order":6},{"code":"J230211","name":"老人憩の家数","unit":"所","year":"2009","value":"59","order":11},{"code":"J230214","name":"老人憩の家従事者数（専任）","unit":"人","year":"2001","value":"32","order":17},{"code":"J230215","name":"老人憩の家従事者数（常勤）","unit":"人","year":"2009","value":"16","order":21},{"code":"J230221","name":"有料老人ホーム数（詳細票）","unit":"所","year":"2023","value":"454","order":13},{"code":"J230222","name":"有料老人ホーム定員数（詳細票）","unit":"人","year":"2023","value":"12932","order":15},{"code":"J230223","name":"有料老人ホーム在所者数（詳細票）","unit":"人","year":"2023","value":"10763","order":15},{"code":"J230225","name":"有料老人ホーム従事者数（詳細票）（常勤）","unit":"人","year":"2023","value":"4642","order":13},{"code":"J2303","name":"その他の社会福祉施設等数","unit":"所","year":"2017","value":"432","order":9},{"code":"J2304","name":"老人福祉施設数（基本票）","unit":"所","year":"2023","value":"107","order":20},{"code":"J230411","name":"養護老人ホーム数（基本票）","unit":"所","year":"2023","value":"35","order":5},{"code":"J230412","name":"養護老人ホーム定員数（基本票）","unit":"人","year":"2023","value":"1840","order":8},{"code":"J230421","name":"有料老人ホーム数（基本票）","unit":"所","year":"2023","value":"454","order":13},{"code":"J230422","name":"有料老人ホーム定員数（基本票）","unit":"人","year":"2023","value":"12831","order":14},{"code":"J230431","name":"軽費老人ホーム数（基本票）","unit":"所","year":"2023","value":"36","order":28},{"code":"J230432","name":"軽費老人ホーム定員数（基本票）","unit":"人","year":"2023","value":"1497","order":24},{"code":"J232101","name":"老人ホーム数","unit":"所","year":"2007","value":"267","order":12},{"code":"J232102","name":"老人ホーム定員数","unit":"人","year":"2007","value":"12025","order":19},{"code":"J232103","name":"老人ホーム在所者数","unit":"人","year":"2007","value":"11515","order":18},{"code":"J232104","name":"老人ホーム従事者数（専任）","unit":"人","year":"2001","value":"4369","order":16},{"code":"J232105","name":"老人ホーム従事者数（常勤）","unit":"人","year":"2007","value":"5960","order":18},{"code":"J2401","name":"身体障害者更生援護施設数","unit":"所","year":"2011","value":"3","order":28},{"code":"J2402","name":"身体障害者更生援護施設定員数","unit":"人","year":"2011","value":"109","order":34},{"code":"J2403","name":"身体障害者更生援護施設在所者数","unit":"人","year":"2011","value":"106","order":30},{"code":"J2404","name":"身体障害者更生援護施設従事者数（専任）","unit":"人","year":"2001","value":"747","order":13},{"code":"J2405","name":"身体障害者更生援護施設従事者数（常勤）","unit":"人","year":"2011","value":"56","order":29},{"code":"J2501","name":"児童福祉施設等数（詳細票）","unit":"所","year":"2023","value":"686","order":17},{"code":"J250101","name":"児童福祉施設等数（詳細票）（保育所等を除く）","unit":"所","year":"2023","value":"198","order":17},{"code":"J250102","name":"児童福祉施設等数（基本票）（保育所等を除く）","unit":"所","year":"2023","value":"217","order":20},{"code":"J250201","name":"児童福祉施設従事者数（保育所、児童館、児童遊園を除く）（専任）","unit":"人","year":"2001","value":"1319","order":9},{"code":"J250202","name":"児童福祉施設等従事者数（詳細票）（常勤）","unit":"人","year":"2023","value":"11364","order":16},{"code":"J250203","name":"児童福祉施設等従事者数（詳細票）（保育所等を除く）（常勤）","unit":"人","year":"2023","value":"2601","order":16},{"code":"J250204","name":"児童福祉施設等数（基本票）","unit":"所","year":"2023","value":"705","order":18},{"code":"J2503","name":"保育所等数（詳細票）","unit":"所","year":"2023","value":"488","order":13},{"code":"J250301","name":"公営保育所等数（詳細票）","unit":"所","year":"2023","value":"74","order":30},{"code":"J250302","name":"保育所等数（基本票）","unit":"所","year":"2023","value":"488","order":13},{"code":"J250303","name":"公営保育所等数（基本票）","unit":"所","year":"2023","value":"78","order":31},{"code":"J2504","name":"保育所保育士数（専任）","unit":"人","year":"2001","value":"5998","order":14},{"code":"J2505","name":"保育所等定員数（詳細票）","unit":"人","year":"2023","value":"41120","order":16},{"code":"J250501","name":"公営保育所等定員数（詳細票）","unit":"人","year":"2023","value":"4391","order":38},{"code":"J250502","name":"保育所等利用待機児童数","unit":"人","year":"2024","value":"4","order":27},{"code":"J2506","name":"保育所等在所児数（詳細票）","unit":"人","year":"2023","value":"37750","order":14},{"code":"J250601","name":"保育所在所児数（3歳児）","unit":"人","year":"2007","value":"8775","order":15},{"code":"J250602","name":"保育所在所児数（4歳児）","unit":"人","year":"2007","value":"9313","order":18},{"code":"J250603","name":"保育所在所児数（5歳児）","unit":"人","year":"2007","value":"9950","order":16},{"code":"J250604","name":"公営保育所等在所児数（詳細票）","unit":"人","year":"2023","value":"3266","order":38},{"code":"J2508","name":"保育所等修了者数（詳細票）","unit":"人","year":"2023","value":"7234","order":14},{"code":"J2509","name":"児童館数","unit":"所","year":"2017","value":"40","order":37},{"code":"J2510","name":"児童遊園数","unit":"所","year":"2011","value":"9","order":27},{"code":"J2511","name":"助産施設数","unit":"所","year":"2007","value":"5","order":27},{"code":"J2513","name":"乳児院数","unit":"所","year":"2007","value":"3","order":11},{"code":"J2514","name":"乳児院定員数","unit":"人","year":"2007","value":"60","order":15},{"code":"J2515","name":"乳児院在所者数","unit":"人","year":"2007","value":"57","order":15},{"code":"J2517","name":"母子生活支援施設数","unit":"所","year":"2007","value":"2","order":39},{"code":"J2519","name":"母子生活支援施設在所者数","unit":"人","year":"2007","value":"97","order":29},{"code":"J2521","name":"児童養護施設数","unit":"所","year":"2007","value":"12","order":15},{"code":"J2522","name":"児童養護施設定員数","unit":"人","year":"2007","value":"786","order":14},{"code":"J2523","name":"児童養護施設在所者数","unit":"人","year":"2007","value":"764","order":11},{"code":"J2525","name":"心身障害児施設数","unit":"所","year":"2007","value":"20","order":13},{"code":"J252501","name":"知的障害児施設数","unit":"所","year":"2007","value":"7","order":14},{"code":"J252502","name":"知的障害児通園施設数","unit":"所","year":"2007","value":"3","order":20},{"code":"J252503","name":"盲児施設数","unit":"所","year":"2007","value":"1","order":1},{"code":"J252504","name":"ろうあ児施設数","unit":"所","year":"2007","value":"1","order":1},{"code":"J252505","name":"難聴幼児通園施設数","unit":"所","year":"2007","value":"1","order":6},{"code":"J252507","name":"肢体不自由児施設数","unit":"所","year":"2007","value":"1","order":15},{"code":"J252508","name":"肢体不自由児通園施設数","unit":"所","year":"2007","value":"1","order":16},{"code":"J252509","name":"肢体不自由児療護施設数","unit":"所","year":"2007","value":"0","order":7},{"code":"J252510","name":"重症心身障害児施設数","unit":"所","year":"2007","value":"4","order":9},{"code":"J252511","name":"情緒障害児短期治療施設数","unit":"所","year":"2007","value":"1","order":4},{"code":"J252512","name":"自閉症児施設数","unit":"所","year":"2007","value":"0","order":6},{"code":"J2526","name":"保育所等保育士数（詳細票）","unit":"人","year":"2023","value":"6480","order":15},{"code":"J252601","name":"公営保育所等保育士数（詳細票）","unit":"人","year":"2023","value":"512","order":39},{"code":"J2527","name":"保育所従事者数（常勤）","unit":"人","year":"2007","value":"8575","order":14},{"code":"J2528","name":"乳児院従事者数（常勤）","unit":"人","year":"2007","value":"71","order":11},{"code":"J2529","name":"母子生活支援施設従事者数（常勤）","unit":"人","year":"2007","value":"14","order":34},{"code":"J2530","name":"児童養護施設従事者数（常勤）","unit":"人","year":"2007","value":"304","order":15},{"code":"J2540","name":"認定こども園数","unit":"園","year":"2024","value":"194","order":23},{"code":"J2541","name":"認定こども園数（幼保連携型）","unit":"園","year":"2024","value":"144","order":18},{"code":"J2542","name":"認定こども園数（幼稚園型）","unit":"園","year":"2024","value":"38","order":13},{"code":"J2543","name":"認定こども園数（保育所型）","unit":"園","year":"2024","value":"12","order":34},{"code":"J2544","name":"認定こども園数（地方裁量型）","unit":"園","year":"2024","value":"0","order":27},{"code":"J2545","name":"幼保連携型認定こども園在所児数","unit":"人","year":"2022","value":"13846","order":16},{"code":"J2546","name":"保育所型認定こども園在所児数","unit":"人","year":"2023","value":"1311","order":29},{"code":"J2547","name":"小規模保育事業所数","unit":"所","year":"2023","value":"86","order":19},{"code":"J2548","name":"小規模保育事業所在所児数","unit":"人","year":"2023","value":"1485","order":18},{"code":"J2626","name":"心身障害児施設定員数","unit":"人","year":"2007","value":"1114","order":12},{"code":"J262601","name":"知的障害児施設定員数","unit":"人","year":"2007","value":"337","order":13},{"code":"J262602","name":"知的障害児通園施設定員数","unit":"人","year":"2007","value":"79","order":31},{"code":"J262608","name":"肢体不自由児通園施設定員数","unit":"人","year":"2007","value":"25","order":22},{"code":"J262610","name":"重症心身障害児施設定員数","unit":"人","year":"2007","value":"509","order":7},{"code":"J2627","name":"心身障害児施設在所者数","unit":"人","year":"2007","value":"1049","order":13},{"code":"J262701","name":"知的障害児施設在所者数","unit":"人","year":"2007","value":"244","order":16},{"code":"J262703","name":"盲児施設在所者数","unit":"人","year":"2007","value":"4","order":8},{"code":"J262709","name":"肢体不自由児療護施設在所者数","unit":"人","year":"2007","value":"0","order":7},{"code":"J2629","name":"児童自立支援施設数","unit":"所","year":"2007","value":"1","order":7},{"code":"J2631","name":"児童自立支援施設在所者数","unit":"人","year":"2007","value":"14","order":36},{"code":"J2633","name":"児童自立支援施設従事者数（常勤）","unit":"人","year":"2007","value":"21","order":29},{"code":"J2634","name":"心身障害児施設従事者数（常勤）","unit":"人","year":"2007","value":"1030","order":9},{"code":"J2641","name":"へき地保育所数","unit":"所","year":"2014","value":"4","order":21},{"code":"J2642","name":"へき地保育所在所児数","unit":"人","year":"2014","value":"29","order":27},{"code":"J2651","name":"認可外保育施設数","unit":"施設","year":"2021","value":"203","order":20},{"code":"J2652","name":"認可外保育施設利用児童数","unit":"人","year":"2021","value":"2998","order":19},{"code":"J2701","name":"知的障害者援護施設数","unit":"所","year":"2011","value":"34","order":9},{"code":"J2702","name":"知的障害者援護施設定員数","unit":"人","year":"2011","value":"1510","order":11},{"code":"J2703","name":"知的障害者援護施設在所者数","unit":"人","year":"2011","value":"1561","order":11},{"code":"J2704","name":"知的障害者援護施設従事者数（専任）","unit":"人","year":"2001","value":"1451","order":16},{"code":"J2705","name":"知的障害者援護施設従事者数（常勤）","unit":"人","year":"2011","value":"639","order":8},{"code":"J2801","name":"母子・父子福祉施設数（詳細票）","unit":"所","year":"2023","value":"2","order":7},{"code":"J2803","name":"母子・父子福祉施設従事者数（詳細票）（常勤）","unit":"人","year":"2023","value":"4","order":14},{"code":"J2804","name":"母子・父子福祉施設数（基本票）","unit":"所","year":"2023","value":"2","order":7},{"code":"J2901","name":"障害者支援施設等数（詳細票）","unit":"所","year":"2023","value":"113","order":17},{"code":"J2902","name":"精神障害者社会復帰施設数","unit":"所","year":"2011","value":"5","order":30},{"code":"J2903","name":"身体障害者社会参加支援施設数","unit":"所","year":"2017","value":"5","order":17},{"code":"J2904","name":"婦人保護施設数（詳細票）","unit":"所","year":"2023","value":"0","order":39},{"code":"J2905","name":"障害者支援施設等数（基本票）","unit":"所","year":"2023","value":"113","order":17},{"code":"J2906","name":"婦人保護施設数（基本票）","unit":"所","year":"2023","value":"0","order":40},{"code":"J3101","name":"民生委員（児童委員）数","unit":"人","year":"2023","value":"4029","order":23},{"code":"J3108","name":"訪問介護員（ホームヘルパー）数","unit":"人","year":"2002","value":"1350","order":19},{"code":"J3201","name":"民生委員（児童委員）相談・支援件数","unit":"件","year":"2023","value":"131625","order":11},{"code":"J3202","name":"福祉事務所生活保護申請件数","unit":"件","year":"2023","value":"3589","order":16},{"code":"J3203","name":"身体障害者更生援護取扱実人員","unit":"人","year":"2007","value":"36993","order":15},{"code":"J3204","name":"福祉事務所知的障害者相談実人員","unit":"人","year":"2002","value":"2270","order":25},{"code":"J3205","name":"身体障害者更生相談所取扱実人員","unit":"人","year":"2023","value":"3592","order":24},{"code":"J3206","name":"知的障害者更生相談所取扱実人員","unit":"人","year":"2023","value":"541","order":41},{"code":"J3207","name":"児童相談所受付件数","unit":"件","year":"2023","value":"6703","order":23},{"code":"J3208","name":"市町村における知的障害者相談実人員","unit":"人","year":"2007","value":"3944","order":26},{"code":"J3209","name":"児童相談所における児童虐待相談の対応件数","unit":"件","year":"2023","value":"2739","order":18},{"code":"J320901","name":"児童相談所における児童虐待相談の対応件数（被虐待者が0～2歳）","unit":"件","year":"2023","value":"505","order":17},{"code":"J320902","name":"児童相談所における児童虐待相談の対応件数（被虐待者が3～6歳）","unit":"件","year":"2023","value":"666","order":20},{"code":"J320903","name":"児童相談所における児童虐待相談の対応件数（被虐待者が7～12歳）","unit":"件","year":"2023","value":"973","order":19},{"code":"J320904","name":"児童相談所における児童虐待相談の対応件数（被虐待者が13～15歳）","unit":"件","year":"2023","value":"401","order":21},{"code":"J320905","name":"児童相談所における児童虐待相談の対応件数（被虐待者が16～18歳）","unit":"件","year":"2023","value":"194","order":20},{"code":"J4001","name":"国民医療費（総額）","unit":"億円","year":"2022","value":"7434","order":15},{"code":"J4002","name":"国民医療費（一般診療）（入院）","unit":"億円","year":"2008","value":"2487","order":15},{"code":"J4003","name":"国民医療費（一般診療）（入院外）","unit":"億円","year":"2008","value":"2060","order":21},{"code":"J4004","name":"一人当たりの医療費","unit":"千円","year":"2022","value":"433","order":8},{"code":"J4005","name":"国民医療費（医科診療）（入院）","unit":"億円","year":"2022","value":"3250","order":14},{"code":"J4006","name":"国民医療費（医科診療）（入院外）","unit":"億円","year":"2022","value":"2404","order":21},{"code":"J4101","name":"国民健康保険被保険者数","unit":"人","year":"2023","value":"353877","order":22},{"code":"J4102","name":"国民健康保険給付件数","unit":"件","year":"2023","value":"6865832","order":18},{"code":"J4104","name":"国民健康保険医療費件数（診療費）","unit":"件","year":"2023","value":"4411183","order":18},{"code":"J4105","name":"国民健康保険給付金額（診療費）（費用額）","unit":"千円","year":"2003","value":"112755856","order":15},{"code":"J4106","name":"国民健康保険被保険者受診率（1000人当たり）","unit":"‐","year":"2023","value":"12081.46","order":9},{"code":"J4107","name":"国民健康保険被保険者1人当たり診療費","unit":"円","year":"2023","value":"381191","order":10},{"code":"J4108","name":"国民健康保険給付金額","unit":"千円","year":"2023","value":"147250034","order":17},{"code":"J4109","name":"国民健康保険医療費金額（診療費）","unit":"千円","year":"2023","value":"139180535","order":16},{"code":"J4201","name":"全国健康保険協会管掌健康保険事業所数","unit":"所","year":"2023","value":"36140","order":21},{"code":"J4202","name":"全国健康保険協会管掌健康保険被保険者数","unit":"人","year":"2023","value":"375329","order":21},{"code":"J4203","name":"全国健康保険協会管掌健康保険被扶養者数","unit":"人","year":"2023","value":"227055","order":22},{"code":"J4204","name":"全国健康保険協会管掌健康保険給付件数","unit":"件","year":"2023","value":"8581696","order":18},{"code":"J420401","name":"政府管掌健康保険給付件数（被保険者）","unit":"件","year":"2006","value":"3211315","order":19},{"code":"J420402","name":"政府管掌健康保険給付件数（被扶養者）","unit":"件","year":"2006","value":"2953871","order":18},{"code":"J420410","name":"全国健康保険協会管掌健康保険給付件数（診療費）","unit":"件","year":"2023","value":"5145741","order":18},{"code":"J420411","name":"全国健康保険協会管掌健康保険給付件数（診療費・被保険者）","unit":"件","year":"2023","value":"3066884","order":18},{"code":"J420412","name":"全国健康保険協会管掌健康保険給付件数（診療費・被扶養者）","unit":"件","year":"2023","value":"2078857","order":19},{"code":"J420421","name":"全国健康保険協会管掌健康保険受診率（被保険者）","unit":"‐","year":"2023","value":"8486.78","order":6},{"code":"J420422","name":"全国健康保険協会管掌健康保険受診率（被扶養者）","unit":"‐","year":"2023","value":"9416.24","order":12},{"code":"J4205","name":"全国健康保険協会管掌健康保険給付金額","unit":"千円","year":"2023","value":"114576452","order":18},{"code":"J420501","name":"政府管掌健康保険給付金額（被保険者）","unit":"千円","year":"2006","value":"37371471","order":18},{"code":"J420502","name":"政府管掌健康保険給付金額（被扶養者）","unit":"千円","year":"2006","value":"30750188","order":18},{"code":"J420510","name":"全国健康保険協会管掌健康保険給付金額（診療費）","unit":"千円","year":"2023","value":"75748346","order":18},{"code":"J420511","name":"全国健康保険協会管掌健康保険給付金額（診療費・被保険者）","unit":"千円","year":"2023","value":"46457430","order":18},{"code":"J420512","name":"全国健康保険協会管掌健康保険給付金額（診療費・被扶養者）","unit":"千円","year":"2023","value":"29290916","order":17},{"code":"J420521","name":"政府管掌健康保険1人当たり受診金額（被保険者）","unit":"円","year":"2007","value":"87667","order":14},{"code":"J420522","name":"政府管掌健康保険1人当たり受診金額（被扶養者）","unit":"円","year":"2007","value":"98696","order":7},{"code":"J420531","name":"全国健康保険協会管掌健康保険1人当たり医療費（被保険者）","unit":"円","year":"2023","value":"202091","order":8},{"code":"J420532","name":"全国健康保険協会管掌健康保険1人当たり医療費（被扶養者）","unit":"円","year":"2023","value":"204670","order":9},{"code":"J420533","name":"全国健康保険協会管掌健康保険1人当たり医療費（加入者合計）","unit":"円","year":"2023","value":"221926","order":8},{"code":"J4206","name":"全国健康保険協会管掌健康保険1人当たり医療費の地域差指数","unit":"－","year":"2023","value":"0.041","order":8},{"code":"J4301","name":"組合管掌健康保険組合数","unit":"組合","year":"2006","value":"7","order":29},{"code":"J4302","name":"組合管掌健康保険被保険者数","unit":"人","year":"2006","value":"18838","order":31},{"code":"J4303","name":"組合管掌健康保険被扶養者数","unit":"人","year":"2006","value":"24583","order":31},{"code":"J4304","name":"組合管掌健康保険給付件数","unit":"件","year":"2006","value":"449578","order":31},{"code":"J430401","name":"組合管掌健康保険給付件数（被保険者）","unit":"件","year":"2006","value":"176084","order":31},{"code":"J430402","name":"組合管掌健康保険給付件数（被扶養者）","unit":"件","year":"2006","value":"269569","order":31},{"code":"J430410","name":"組合管掌健康保険給付件数（診療費）","unit":"件","year":"2006","value":"307708","order":31},{"code":"J430411","name":"組合管掌健康保険給付件数（診療費・被保険者）","unit":"件","year":"2006","value":"123234","order":31},{"code":"J430412","name":"組合管掌健康保険給付件数（診療費・被扶養者）","unit":"件","year":"2006","value":"184474","order":31},{"code":"J430421","name":"組合管掌健康保険受診率（被保険者）","unit":"‐","year":"2006","value":"6551.17","order":18},{"code":"J430422","name":"組合管掌健康保険受診率（被扶養者）","unit":"‐","year":"2006","value":"7801.82","order":12},{"code":"J4305","name":"組合管掌健康保険給付金額","unit":"千円","year":"2006","value":"4384979","order":31},{"code":"J430501","name":"組合管掌健康保険給付金額（被保険者）","unit":"千円","year":"2006","value":"1654847","order":31},{"code":"J430502","name":"組合管掌健康保険給付金額（被扶養者）","unit":"千円","year":"2006","value":"2163412","order":30},{"code":"J430510","name":"組合管掌健康保険給付金額（診療費）","unit":"千円","year":"2006","value":"3149978","order":31},{"code":"J430511","name":"組合管掌健康保険給付金額（診療費・被保険者）","unit":"千円","year":"2006","value":"1392760","order":31},{"code":"J430512","name":"組合管掌健康保険給付金額（診療費・被扶養者）","unit":"千円","year":"2006","value":"1757218","order":30},{"code":"J430521","name":"組合管掌健康保険1人当たり受診金額（被保険者）","unit":"円","year":"2006","value":"74040","order":13},{"code":"J4401","name":"船員保険（疾病分）船舶所有者数","unit":"人","year":"2006","value":"211","order":7},{"code":"J4402","name":"船員保険（疾病分）被保険者数","unit":"人","year":"2006","value":"1395","order":16},{"code":"J4403","name":"船員保険（疾病分）被扶養者数","unit":"人","year":"2006","value":"2341","order":15},{"code":"J4404","name":"船員保険（疾病分）給付件数","unit":"件","year":"2006","value":"48458","order":13},{"code":"J440401","name":"船員保険（疾病分）給付件数（被保険者）","unit":"件","year":"2006","value":"13305","order":18},{"code":"J440402","name":"船員保険（疾病分）給付件数（被扶養者）","unit":"件","year":"2006","value":"32419","order":10},{"code":"J440410","name":"船員保険（疾病分）給付件数（診療費）","unit":"件","year":"2006","value":"29891","order":13},{"code":"J440411","name":"船員保険（疾病分）給付件数（診療費・被保険者）","unit":"件","year":"2006","value":"8772","order":18},{"code":"J440412","name":"船員保険（疾病分）給付件数（診療費・被扶養者）","unit":"件","year":"2006","value":"21119","order":10},{"code":"J4405","name":"船員保険（疾病分）給付金額","unit":"千円","year":"2006","value":"626344","order":15},{"code":"J440501","name":"船員保険（疾病分）給付金額（被保険者）","unit":"千円","year":"2006","value":"264686","order":20},{"code":"J440502","name":"船員保険（疾病分）給付金額（被扶養者）","unit":"千円","year":"2006","value":"319271","order":11},{"code":"J440510","name":"船員保険（疾病分）給付金額（診療費）","unit":"千円","year":"2006","value":"398818","order":15},{"code":"J440511","name":"船員保険（疾病分）給付金額（診療費・被保険者）","unit":"千円","year":"2006","value":"162584","order":17},{"code":"J440512","name":"船員保険（疾病分）給付金額（診療費・被扶養者）","unit":"千円","year":"2006","value":"236234","order":11},{"code":"J4501","name":"後期高齢者医療被保険者数","unit":"人","year":"2023","value":"293732","order":22},{"code":"J4502","name":"老人医療受給件数","unit":"件","year":"2007","value":"6674632","order":19},{"code":"J450210","name":"老人医療受給件数（診療費）","unit":"件","year":"2007","value":"4384114","order":18},{"code":"J450220","name":"老人医療受診率（1000人当たり）","unit":"‐","year":"2007","value":"18227.50","order":19},{"code":"J4503","name":"後期高齢者医療費","unit":"千円","year":"2023","value":"324240862","order":15},{"code":"J450310","name":"老人医療費（診療費）","unit":"千円","year":"2007","value":"187127586","order":14},{"code":"J450320","name":"1人当たり後期高齢者医療費","unit":"円","year":"2023","value":"1103868","order":7},{"code":"J5101","name":"厚生年金保険適用事業所数","unit":"所","year":"2022","value":"35260","order":21},{"code":"J5102","name":"厚生年金保険被保険者数","unit":"人","year":"2022","value":"417789","order":22},{"code":"J5103","name":"厚生年金保険受給権者数","unit":"人","year":"2022","value":"547892","order":23},{"code":"J510301","name":"厚生年金保険受給権者数（老齢年金）","unit":"人","year":"2006","value":"148839","order":25},{"code":"J510302","name":"厚生年金保険受給権者数（通算老齢年金）","unit":"人","year":"2006","value":"137351","order":23},{"code":"J510303","name":"厚生年金保険受給権者数（障害年金）","unit":"人","year":"2006","value":"8850","order":19},{"code":"J510304","name":"厚生年金保険受給権者数（遺族年金）","unit":"人","year":"2006","value":"59201","order":27},{"code":"J510305","name":"厚生年金保険受給権者数（通算遺族年金）","unit":"人","year":"2006","value":"1291","order":25},{"code":"J5104","name":"厚生年金保険受給権者年金総額","unit":"千円","year":"2022","value":"304830141","order":26},{"code":"J510401","name":"厚生年金保険受給権者年金総額（老齢年金）","unit":"千円","year":"2006","value":"190665842","order":28},{"code":"J5201","name":"国民年金被保険者数","unit":"人","year":"2022","value":"261689","order":23},{"code":"J520101","name":"国民年金第1号被保険者数","unit":"人","year":"2022","value":"183467","order":22},{"code":"J520102","name":"国民年金第3号被保険者数","unit":"人","year":"2022","value":"78222","order":26},{"code":"J520111","name":"国民年金保険料全額免除割合","unit":"％","year":"2006","value":"27","order":24},{"code":"J520112","name":"国民年金保険料申請一部免除割合","unit":"％","year":"2006","value":"3","order":22},{"code":"J520120","name":"国民年金保険料納付率","unit":"％","year":"2022","value":"74.7","order":38},{"code":"J5202","name":"国民年金受給権者数","unit":"人","year":"2022","value":"581960","order":22},{"code":"J520201","name":"国民年金受給権者数（老齢年金）","unit":"人","year":"2006","value":"372031","order":20},{"code":"J520202","name":"国民年金受給権者数（通算老齢年金）","unit":"人","year":"2006","value":"24997","order":17},{"code":"J520203","name":"国民年金受給権者数（障害年金）","unit":"人","year":"2006","value":"37576","order":14},{"code":"J520204","name":"国民年金受給権者数（遺族年金）","unit":"人","year":"2006","value":"5574","order":23},{"code":"J5203","name":"国民年金受給権者年金総額","unit":"千円","year":"2022","value":"398072014","order":22},{"code":"J520301","name":"国民年金受給権者年金総額（老齢年金）","unit":"千円","year":"2006","value":"235282743","order":21},{"code":"J5301","name":"福祉年金受給者数","unit":"人","year":"2022","value":"-","order":null},{"code":"J5302","name":"福祉年金支給年額","unit":"千円","year":"2022","value":"-","order":null},{"code":"J6101","name":"雇用保険適用事業所数","unit":"所","year":"2023","value":"35453","order":18},{"code":"J6102","name":"雇用保険被保険者数","unit":"人","year":"2023","value":"502297","order":23},{"code":"J6103","name":"雇用保険求職者給付支給額","unit":"円","year":"2023","value":"10870527643","order":16},{"code":"J6104","name":"雇用保険基本手当支給額","unit":"円","year":"2023","value":"10718207006","order":16},{"code":"J6105","name":"雇用保険基本手当受給者実人員","unit":"人","year":"2023","value":"7338","order":16},{"code":"J6106","name":"雇用保険基本手当受給資格決定件数","unit":"件","year":"2007","value":"32987","order":15},{"code":"J6107","name":"雇用保険基本手当初回受給者数","unit":"人","year":"2007","value":"27734","order":15},{"code":"J610701","name":"雇用保険基本手当初回受給者数（45歳以上）","unit":"人","year":"2007","value":"11567","order":16},{"code":"J6109","name":"雇用保険（日雇）労働被保険者数","unit":"人","year":"2023","value":"2","order":29},{"code":"J6110","name":"雇用保険（日雇）受給者実人員","unit":"人","year":"2023","value":"0","order":32},{"code":"J6111","name":"雇用保険（日雇）給付支給額","unit":"千円","year":"2023","value":"38","order":35},{"code":"J6201","name":"船員保険（失業分）船舶所有者数","unit":"人","year":"2006","value":"165","order":8},{"code":"J6202","name":"船員保険（失業分）被保険者数","unit":"人","year":"2006","value":"1114","order":15},{"code":"J6203","name":"船員保険（失業分）失業保険金給付件数","unit":"件","year":"2006","value":"314","order":15},{"code":"J6204","name":"船員保険（失業分）失業保険金給付金額","unit":"千円","year":"2006","value":"43609","order":17},{"code":"J6301","name":"労働者災害補償保険適用事業場数","unit":"事業場","year":"2023","value":"44742","order":20},{"code":"J6302","name":"労働者災害補償保険適用労働者数","unit":"人","year":"2023","value":"643657","order":23},{"code":"J6303","name":"労働者災害補償保険給付件数","unit":"件","year":"2023","value":"56396","order":22},{"code":"J6304","name":"労働者災害補償保険給付支給額","unit":"円","year":"2023","value":"3908964828","order":18},{"code":"J7101","name":"介護保険給付（件数）","unit":"件","year":"2023","value":"2331068","order":20},{"code":"J710101","name":"居宅介護（支援）サービス介護給付（件数）","unit":"件","year":"2007","value":"1004921","order":25},{"code":"J710102","name":"施設介護サービス介護給付（件数）","unit":"件","year":"2007","value":"207204","order":16},{"code":"J7102","name":"介護保険給付（費用額）","unit":"千円","year":"2023","value":"178016204","order":21},{"code":"J710201","name":"居宅介護（支援）サービス介護給付（費用額）","unit":"千円","year":"2007","value":"40749519","order":24},{"code":"J710202","name":"施設介護サービス介護給付（費用額）","unit":"千円","year":"2007","value":"60815600","order":14},{"code":"J7103","name":"介護保険給付（支給額）","unit":"千円","year":"2023","value":"159926143","order":21},{"code":"J710301","name":"居宅介護（支援）サービス介護給付（支給額）","unit":"千円","year":"2007","value":"37040338","order":24},{"code":"J710302","name":"施設介護サービス介護給付（支給額）","unit":"千円","year":"2007","value":"54886217","order":14}]